gaimin_ai/__init__.py
gaimin_ai/client.py
gaimin_ai/http_client.py
gaimin_ai/api/__init__.py
gaimin_ai/api/speech_to_text.py
gaimin_ai/api/text_to_image.py
gaimin_ai/api/text_to_speech.py
gaimin_ai/api/text_to_text.py
gaimin_ai/models/__init__.py
gaimin_ai/models/s2t.py
gaimin_ai/models/t2i.py
gaimin_ai/models/t2s.py
gaimin_ai/models/t2t.py
gaimin_ai-0.1.5.dist-info/LICENSE
gaimin_ai-0.1.5.dist-info/METADATA
gaimin_ai-0.1.5.dist-info/WHEEL
gaimin_ai-0.1.5.dist-info/top_level.txt
gaimin_ai-0.1.5.dist-info/RECORD
